alyx_setup_utils-0.2.0.dist-info/METADATA
alyx_setup_utils-0.2.0.dist-info/WHEEL
alyx_setup_utils-0.2.0.dist-info/entry_points.txt
alyx_setup_utils/__init__.py
alyx_setup_utils-0.2.0.dist-info/RECORD
